PrepData/__init__.py
PrepData/prepDF.py
tests/__init__.py
tests/test_prepDF.py
PrepData-0.1.12.dist-info/LICENSE.txt
PrepData-0.1.12.dist-info/METADATA
PrepData-0.1.12.dist-info/WHEEL
PrepData-0.1.12.dist-info/top_level.txt
PrepData-0.1.12.dist-info/RECORD
