Metadata-Version: 2.1
Name: PrepData
Version: 0.1.12
Summary: Automating the process of Data Preprocessing for Data Science
Home-page: https://github.com/Karan-Malik/prepdata
Author: Karan Malik
Author-email: karanmalik2000@gmail.com
License: MIT
Platform: UNKNOWN
Requires-Dist: joblib (==1.0.1)
Requires-Dist: numpy (==1.20.1)
Requires-Dist: pandas (==1.2.2)
Requires-Dist: python-dateutil (==2.8.1)
Requires-Dist: pytz (==2021.1)
Requires-Dist: scikit-learn (==0.24.1)
Requires-Dist: scipy (==1.6.1)
Requires-Dist: setuptools (==52.0.0)
Requires-Dist: sip (==6.0.1)
Requires-Dist: six (==1.15.0)
Requires-Dist: sklearn (==0.0)
Requires-Dist: threadpoolctl (==2.1.0)
Requires-Dist: wheel (==0.36.2)
Requires-Dist: wincertstore (==0.2)
Requires-Dist: nltk (==3.5)
